vuefinder/__init__.py
vuefinder_wsgi-1.6.1.dist-info/licenses/LICENSE
vuefinder_wsgi-1.6.1.dist-info/METADATA
vuefinder_wsgi-1.6.1.dist-info/WHEEL
vuefinder_wsgi-1.6.1.dist-info/top_level.txt
vuefinder_wsgi-1.6.1.dist-info/RECORD
