Metadata-Version: 2.4
Name: vuefinder-wsgi
Version: 1.6.1
Summary: WSGI app to use PyFilesystem2 with vuefinder
Author-email: Andreas Bichinger <andreas.bichinger@gmail.com>
Project-URL: Homepage, https://github.com/abichinger/vuefinder-wsgi
Project-URL: Issues, https://github.com/abichinger/vuefinder-wsgi/issues
Keywords: vuefinder,pyfilesystem,file explorer
Classifier: Programming Language :: Python :: 3
Classifier: License :: OSI Approved :: MIT License
Classifier: Operating System :: OS Independent
Requires-Python: >=3.8
License-File: LICENSE
Requires-Dist: Werkzeug
Requires-Dist: fs
Requires-Dist: pathvalidate==3.2.1
Dynamic: license-file
